yadocgen/__init__.py
yadocgen/example.py
yadocgen/generator.py
yadocgen/rendering.py
yadocgen/templates/Makefile.jinja
yadocgen/templates/__init__.py
yadocgen/templates/api_index.rst.jinja
yadocgen/templates/conf.py.jinja
yadocgen/templates/docpage.md.jinja
yadocgen/templates/module.rst.jinja
yadocgen/templates/package.rst.jinja
yadocgen/templates/welcome.md.jinja
yadocgen-0.1.5.dist-info/LICENSE
yadocgen-0.1.5.dist-info/METADATA
yadocgen-0.1.5.dist-info/WHEEL
yadocgen-0.1.5.dist-info/entry_points.txt
yadocgen-0.1.5.dist-info/top_level.txt
yadocgen-0.1.5.dist-info/RECORD
