Metadata-Version: 2.1
Name: yadocgen
Version: 0.1.5
Summary: Yet Another Documentation Generator
Home-page: https://github.com/fraunhofer-iais/yadocgen
Author: Ben Wulff
Author-email: benjamin.wulff@iais.fraunhofer.de
License: UNKNOWN
Platform: UNKNOWN
License-File: LICENSE
Requires-Dist: click
Requires-Dist: pypandoc
Requires-Dist: anytree
Requires-Dist: bunch
Requires-Dist: jinja2
Requires-Dist: pyyaml
Requires-Dist: sphinx
Requires-Dist: myst-parser
Requires-Dist: linkify-it-py
Requires-Dist: karma-sphinx-theme
Requires-Dist: sphinxcontrib-bibtex
Requires-Dist: numpy
Requires-Dist: matplotlib
Requires-Dist: numpydoc
